genie.libs.sdk-24.6-py3.11-nspkg.pth
genie/libs/sdk/__init__.py
genie/libs/sdk/apis/__init__.py
genie/libs/sdk/apis/api_unittest_generator.py
genie/libs/sdk/apis/apis.json
genie/libs/sdk/apis/execute.py
genie/libs/sdk/apis/utils.py
genie/libs/sdk/apis/verify.py
genie/libs/sdk/apis/aireos/__init__.py
genie/libs/sdk/apis/aireos/get.py
genie/libs/sdk/apis/aireos/verify.py
genie/libs/sdk/apis/apic/__init__.py
genie/libs/sdk/apis/apic/utils.py
genie/libs/sdk/apis/apic/acidiag/__init__.py
genie/libs/sdk/apis/apic/acidiag/get.py
genie/libs/sdk/apis/apic/acidiag/verify.py
genie/libs/sdk/apis/apic/fabric/__init__.py
genie/libs/sdk/apis/apic/fabric/execute.py
genie/libs/sdk/apis/apic/firmware/__init__.py
genie/libs/sdk/apis/apic/firmware/execute.py
genie/libs/sdk/apis/apic/firmware/get.py
genie/libs/sdk/apis/apic/firmware/verify.py
genie/libs/sdk/apis/apic/platform/__init__.py
genie/libs/sdk/apis/apic/platform/get.py
genie/libs/sdk/apis/apic/platform/utils.py
genie/libs/sdk/apis/apic/platform/verify.py
genie/libs/sdk/apis/apic/support/__init__.py
genie/libs/sdk/apis/apic/support/tech_support.py
genie/libs/sdk/apis/asa/__init__.py
genie/libs/sdk/apis/asa/running_config/__init__.py
genie/libs/sdk/apis/asa/running_config/get.py
genie/libs/sdk/apis/cheetah/__init__.py
genie/libs/sdk/apis/cheetah/ap/__init__.py
genie/libs/sdk/apis/cheetah/ap/execute.py
genie/libs/sdk/apis/cheetah/ap/get.py
genie/libs/sdk/apis/cheetah/ap/verify.py
genie/libs/sdk/apis/ios/__init__.py
genie/libs/sdk/apis/ios/platform.py
genie/libs/sdk/apis/ios/utils.py
genie/libs/sdk/apis/ios/cdp/__init__.py
genie/libs/sdk/apis/ios/cdp/configure.py
genie/libs/sdk/apis/ios/cdp/get.py
genie/libs/sdk/apis/ios/cdp/verify.py
genie/libs/sdk/apis/ios/interface/__init__.py
genie/libs/sdk/apis/ios/interface/configure.py
genie/libs/sdk/apis/ios/interface/get.py
genie/libs/sdk/apis/ios/lldp/__init__.py
genie/libs/sdk/apis/ios/lldp/configure.py
genie/libs/sdk/apis/ios/lldp/get.py
genie/libs/sdk/apis/ios/lldp/verify.py
genie.libs.sdk-24.6.dist-info/METADATA
genie.libs.sdk-24.6.dist-info/WHEEL
genie.libs.sdk-24.6.dist-info/entry_points.txt
genie.libs.sdk-24.6.dist-info/namespace_packages.txt
genie.libs.sdk-24.6.dist-info/top_level.txt
genie.libs.sdk-24.6.dist-info/RECORD
